django_package_monitor-0.6.1.dist-info/METADATA
django_package_monitor-0.6.1.dist-info/RECORD
django_package_monitor-0.6.1.dist-info/WHEEL
django_package_monitor-0.6.1.dist-info/top_level.txt
package_monitor/__init__.py
package_monitor/admin.py
package_monitor/apps.py
package_monitor/compat.py
package_monitor/models.py
package_monitor/pypi.py
package_monitor/settings.py
package_monitor/urls.py
package_monitor/views.py
package_monitor/management/__init__.py
package_monitor/management/commands/__init__.py
package_monitor/management/commands/refresh_packages.py
package_monitor/migrations/0001_initial.py
package_monitor/migrations/0002_auto_20151126_1453.py
package_monitor/migrations/0003_packageversion_next_version.py
package_monitor/migrations/0004_auto_20160109_1339.py
package_monitor/migrations/0005_packageversion_is_parseable.py
package_monitor/migrations/0006_add_python_version_info.py
package_monitor/migrations/0007_add_django_version_info.py
package_monitor/migrations/__init__.py
package_monitor/templates/_package.html
package_monitor/templates/_package.txt
package_monitor/templates/change_list.html
package_monitor/templates/summary.html
package_monitor/templates/summary.txt
package_monitor/tests/__init__.py
package_monitor/tests/test_migrations.py
package_monitor/tests/test_models.py
package_monitor/tests/test_pypi.py
