Metadata-Version: 2.1
Name: django-package-monitor
Version: 0.6.1
Summary: Requirements package monitor for Django projects.
Home-page: https://github.com/yunojuno/django-package-monitor
Author: YunoJuno
Author-email: cod@yunojuno.com
License: MIT
Platform: UNKNOWN
Classifier: Environment :: Web Environment
Classifier: Intended Audience :: Developers
Classifier: License :: OSI Approved :: MIT License
Classifier: Operating System :: OS Independent
Classifier: Framework :: Django
Classifier: Framework :: Django :: 1.11
Classifier: Framework :: Django :: 2.0
Classifier: Programming Language :: Python
Classifier: Programming Language :: Python :: 3.6
Classifier: Topic :: Internet :: WWW/HTTP
Classifier: Topic :: Internet :: WWW/HTTP :: Dynamic Content
Requires-Dist: django (>=1.11)
Requires-Dist: requests (>=2.0)
Requires-Dist: requirements-parser (==0.1.0)
Requires-Dist: semantic-version (>=2.5)
